osutools/__init__.py
osutools/db.py
osutools/exceptions.py
osutools/map.py
osutools/match.py
osutools/oppai.py
osutools/osuclient.py
osutools/score.py
osutools/user.py
osutools/utils.py
osutools/oppai_files/liboppai.so
osutools/oppai_files/liboppaii686.so
osutools/oppai_files/oppai.dll
osutools/oppai_files/oppai32.dll
osu_tools-0.2.13.dist-info/LICENSE.md
osu_tools-0.2.13.dist-info/METADATA
osu_tools-0.2.13.dist-info/WHEEL
osu_tools-0.2.13.dist-info/top_level.txt
osu_tools-0.2.13.dist-info/RECORD
