Metadata-Version: 2.1
Name: osu-tools
Version: 0.2.13
Summary: A python wrapper for working with the osu! API, databases and file formats
Home-page: https://github.com/largereptile/osutools
Author: largereptile
Author-email: harry@barold.dev
License: MIT
Platform: UNKNOWN
Requires-Python: >=3
License-File: LICENSE.md
Requires-Dist: requests (>=2.25.1)
